qlearn/__init__.py
qlearn/classification.py
qlearn/clustering.py
qlearn/qfm.py
qlearn/regression.py
qlearn/vqc.py
qlearn/backends/__init__.py
qlearn/backends/base.py
qlearn/pennylane/__init__.py
qlearn/pennylane/qfm.py
qlearn/pennylane/vqc.py
qlearn/qiskit/__init__.py
qlearn/qiskit/qfm.py
qlearn/qiskit/vqc.py
quantum_learn-1.0.1.dist-info/licenses/LICENSE
quantum_learn-1.0.1.dist-info/METADATA
quantum_learn-1.0.1.dist-info/WHEEL
quantum_learn-1.0.1.dist-info/top_level.txt
quantum_learn-1.0.1.dist-info/RECORD
