Metadata-Version: 2.4
Name: quantum-learn
Version: 1.0.1
Summary: quantum-learn: quantum machine learning in Python
Author-email: OsamaMIT <author@example.com>
License: MIT
Classifier: Programming Language :: Python :: 3
Classifier: License :: OSI Approved :: MIT License
Classifier: Operating System :: OS Independent
Classifier: Development Status :: 3 - Alpha
Classifier: Topic :: Scientific/Engineering :: Artificial Intelligence
Requires-Python: >=3.6
License-File: LICENSE
Requires-Dist: pennylane
Requires-Dist: pandas
Requires-Dist: scikit-learn
Dynamic: license-file
